odoo/addons/users_ldap_groups/README.rst
odoo/addons/users_ldap_groups/__init__.py
odoo/addons/users_ldap_groups/__manifest__.py
odoo/addons/users_ldap_groups/i18n/de.po
odoo/addons/users_ldap_groups/i18n/es.po
odoo/addons/users_ldap_groups/i18n/fr.po
odoo/addons/users_ldap_groups/i18n/hr.po
odoo/addons/users_ldap_groups/i18n/pt_BR.po
odoo/addons/users_ldap_groups/i18n/sl.po
odoo/addons/users_ldap_groups/i18n/users_ldap_groups.pot
odoo/addons/users_ldap_groups/models/__init__.py
odoo/addons/users_ldap_groups/models/res_company_ldap.py
odoo/addons/users_ldap_groups/models/res_company_ldap_group_mapping.py
odoo/addons/users_ldap_groups/models/res_company_ldap_operator.py
odoo/addons/users_ldap_groups/models/res_users.py
odoo/addons/users_ldap_groups/readme/CONTRIBUTORS.rst
odoo/addons/users_ldap_groups/readme/DESCRIPTION.rst
odoo/addons/users_ldap_groups/readme/USAGE.rst
odoo/addons/users_ldap_groups/security/ir.model.access.csv
odoo/addons/users_ldap_groups/static/description/icon.png
odoo/addons/users_ldap_groups/static/description/index.html
odoo/addons/users_ldap_groups/tests/__init__.py
odoo/addons/users_ldap_groups/tests/test_users_ldap_groups.py
odoo/addons/users_ldap_groups/views/res_company_ldap_views.xml
odoo13_addon_users_ldap_groups-13.0.1.0.1.dist-info/METADATA
odoo13_addon_users_ldap_groups-13.0.1.0.1.dist-info/WHEEL
odoo13_addon_users_ldap_groups-13.0.1.0.1.dist-info/top_level.txt
odoo13_addon_users_ldap_groups-13.0.1.0.1.dist-info/RECORD
